complexint.cpython-311-i386-linux-gnu.so
complexint-stubs/__init__.pyi
complexint-0.0.6.dist-info/METADATA
complexint-0.0.6.dist-info/WHEEL
complexint-0.0.6.dist-info/top_level.txt
complexint-0.0.6.dist-info/RECORD
complexint-0.0.6.dist-info/licenses/LICENSE
