Metadata-Version: 2.4
Name: complexint
Version: 0.0.6
Summary: A complexint class, for using large complex numbers which exceed the precision offered by the builtin complex which uses doubles.
Author-email: Ryan Heard <ryanwheard@gmail.com>
License: MIT
Project-URL: Repository, https://github.com/rheard/complexint
Keywords: complex,math
Classifier: Programming Language :: Python :: 3
Classifier: Programming Language :: Python :: 3.8
Classifier: Programming Language :: Python :: 3.9
Classifier: Programming Language :: Python :: 3.10
Classifier: Programming Language :: Python :: 3.11
Classifier: Programming Language :: Python :: 3.12
Classifier: Programming Language :: Python :: 3.13
Classifier: Programming Language :: Python :: Implementation :: CPython
Requires-Python: >=3.8
License-File: LICENSE
Dynamic: license
Dynamic: license-file
